[{"demonym": "British", "latlng": [54, -2], "gini": 34, "area": 242900, "timezones": ["UTC-08:00", "UTC-05:00", "UTC-04:00", "UTC-03:00", "UTC-02:00", "UTC", "UTC+01:00", "UTC+02:00", "UTC+06:00"], "alpha3Code": "GBR", "borders": ["IRL"], "population": 64800000, "relevance": "2.5", "languages": ["en"], "translations": {"es": "Reino Unido", "ja": "\u30a4\u30ae\u30ea\u30b9", "fr": "Royaume-Uni", "it": "Regno Unito", "de": "Vereinigtes K\u00f6nigreich"}, "name": "United Kingdom", "topLevelDomain": [".uk"], "capital": "London", "nativeName": "United Kingdom", "subregion": "Northern Europe", "alpha2Code": "GB", "currencies": ["GBP"], "region": "Europe", "altSpellings": ["GB", "UK", "Great Britain"], "callingCodes": ["44"], "numericCode": "826"}, {"demonym": "Italian", "latlng": [42.83333333, 12.83333333], "gini": 36, "area": 301336, "timezones": ["UTC+01:00"], "alpha3Code": "ITA", "borders": ["AUT", "FRA", "SMR", "SVN", "CHE", "VAT"], "population": 60753794, "relevance": "2", "languages": ["it"], "translations": {"es": "Italia", "ja": "\u30a4\u30bf\u30ea\u30a2", "fr": "Italie", "it": "Italia", "de": "Italien"}, "name": "Italy", "topLevelDomain": [".it"], "capital": "Rome", "nativeName": "Italia", "subregion": "Southern Europe", "alpha2Code": "IT", "currencies": ["EUR"], "region": "Europe", "altSpellings": ["IT", "Italian Republic", "Repubblica italiana"], "callingCodes": ["39"], "numericCode": "380"}, {"demonym": "American", "latlng": [38, -97], "gini": 48, "area": 9629091, "timezones": ["UTC-12:00", "UTC-11:00", "UTC-10:00", "UTC-09:00", "UTC-08:00", "UTC-07:00", "UTC-06:00", "UTC-05:00", "UTC-04:00", "UTC+10:00", "UTC+12:00"], "alpha3Code": "USA", "borders": ["CAN", "MEX"], "population": 321645000, "relevance": "3.5", "languages": ["en"], "translations": {"es": "Estados Unidos", "ja": "\u30a2\u30e1\u30ea\u30ab\u5408\u8846\u56fd", "fr": "\u00c9tats-Unis", "it": "Stati Uniti D'America", "de": "Vereinigte Staaten von Amerika"}, "name": "United States", "topLevelDomain": [".us"], "capital": "Washington, D.C.", "nativeName": "United States", "subregion": "Northern America", "alpha2Code": "US", "currencies": ["USD", "USN", "USS"], "region": "Americas", "altSpellings": ["US", "USA", "United States of America"], "callingCodes": ["1"], "numericCode": "840"}]